Metadata-Version: 2.1
Name: test_package_Wajdi_jomaa
Version: 0.1.0
Summary: A brief description of your package
Home-page: https://github.com/yourusername/your-package
Author: wajdi jomaa
Author-email: blackwajdi9@gmail.com
Classifier: Programming Language :: Python :: 3
Classifier: License :: OSI Approved :: MIT License
Classifier: Operating System :: OS Independent
Requires-Python: >=3.6
License-File: LICENSE
